msal_streamlit_authentication/__init__.py
msal_streamlit_authentication/frontend/dist/assets/index-297265e4.css
msal_streamlit_authentication/frontend/dist/assets/index-95ea6472.js
msal_streamlit_authentication/frontend/dist/index.html
msal_streamlit_authentication/main.py
msal_streamlit_authentication_options-1.0.9.dist-info/LICENSE
msal_streamlit_authentication_options-1.0.9.dist-info/METADATA
msal_streamlit_authentication_options-1.0.9.dist-info/WHEEL
msal_streamlit_authentication_options-1.0.9.dist-info/RECORD
